libry/__init__.py
libry/squareroot.py
root_calculator-0.0.1.dist-info/LICENSE
root_calculator-0.0.1.dist-info/METADATA
root_calculator-0.0.1.dist-info/WHEEL
root_calculator-0.0.1.dist-info/top_level.txt
root_calculator-0.0.1.dist-info/RECORD
